<?xml version="1.1" encoding="UTF-8"?>
<expression:EMFExpression xmi:version="2.0" xmlns:xmi="http://www.omg.org/XMI" xmlns:expression="http:///expression.ecore" id="tMap_1=>" expression="row1.valor_causa == null || row1.valor_causa.isEmpty() ? null : new BigDecimal(row1.valor_causa)">
  <variables name="row1.id_processo" value="0" talendType="id_Integer"/>
  <variables name="row1.numero_processo" value="null" talendType="id_String"/>
  <variables name="row1.id_tribunal" value="null" talendType="id_String"/>
  <variables name="row1.id_classe" value="null" talendType="id_String"/>
  <variables name="row1.id_assunto" value="null" talendType="id_String"/>
  <variables name="row1.id_magistrado" value="null" talendType="id_String"/>
  <variables name="row1.data_ajuizamento" value="null" talendType="id_Date"/>
  <variables name="row1.tempo_processo_dias" value="null" talendType="id_String"/>
  <variables name="row1.valor_causa" value="null" talendType="id_String"/>
</expression:EMFExpression>
